enhanced_enums/__init__.py
enhanced_enums/enhanced_enums.py
enhanced_enums/infos.py
enhanced_enums-1.0.2.dist-info/LICENSE
enhanced_enums-1.0.2.dist-info/METADATA
enhanced_enums-1.0.2.dist-info/WHEEL
enhanced_enums-1.0.2.dist-info/top_level.txt
enhanced_enums-1.0.2.dist-info/RECORD
