Metadata-Version: 2.1
Name: enhanced-enums
Version: 1.0.2
Summary: A package that provides enhanced enums for Python.
Home-page: https://github.com/m-ghiani/ENHANCED_ENUMS
Author: Massimo Ghiani
Author-email: m.ghiani@gmail.com
Maintainer: Massimo Ghiani <m.ghiani@gmail.com>
Maintainer-email: m.ghiani@gmail.com
License: MIT
Project-URL: Bug Reports, https://github.com/m-ghiani/ENHANCED_ENUMS/issues
Project-URL: Source, https://github.com/m-ghiani/ENHANCED_ENUMS
Keywords: enum,enums,enhanced,enhanced enums,enhanced enum,enhanced-enums,enhanced-enum,enhancedenums,enhancedenum,enhancedenum,enhanced_enums,enhanced_enum,enhancedenums,enhancedenum,enhancedenum,enhanced-enums-package,enhanced-enums-package,enhanced_enums_package,enhanced_enums_package,enhanced-enums,enhanced-enums,enhanced_enums,enhanced_enums,enhanced,en
Classifier: Development Status :: 5 - Production/Stable
Classifier: Intended Audience :: Developers
Classifier: License :: OSI Approved :: MIT License
Classifier: Programming Language :: Python :: 3.10
Classifier: Programming Language :: Python :: 3.11
Classifier: Programming Language :: Python :: 3.12
Requires-Python: >=3.10
License-File: LICENSE
